biased_stop_words/__init__.py
biased_stop_words/tests.py
biased_stop_words/biased-stop-words/en-gendered.txt
biased_stop_words/biased-stop-words/gendered-adjectives.txt
biased_stop_words/biased-stop-words/gendered-nouns.txt
biased_stop_words/biased-stop-words/mapping.yaml
biased_stop_words/biased-stop-words/us-names.txt
biased_stop_words-2017.5.12.1.dist-info/DESCRIPTION.rst
biased_stop_words-2017.5.12.1.dist-info/METADATA
biased_stop_words-2017.5.12.1.dist-info/RECORD
biased_stop_words-2017.5.12.1.dist-info/WHEEL
biased_stop_words-2017.5.12.1.dist-info/metadata.json
biased_stop_words-2017.5.12.1.dist-info/top_level.txt
