Metadata-Version: 2.0
Name: biased-stop-words
Version: 2017.5.12.1
Summary: Generates biased stop word lists for various genres
Home-page: https://github.com/gregology/python-biased-stop-words
Author: Greg Clarke
Author-email: greg@gho.st
License: MIT
Keywords: stopwords data bias
Platform: UNKNOWN
Classifier: Development Status :: 4 - Beta
Classifier: Intended Audience :: Developers
Classifier: Topic :: Software Development :: Build Tools
Classifier: License :: OSI Approved :: MIT License
Classifier: Programming Language :: Python :: 2
Classifier: Programming Language :: Python :: 2.6
Classifier: Programming Language :: Python :: 2.7
Classifier: Programming Language :: Python :: 3
Classifier: Programming Language :: Python :: 3.2
Classifier: Programming Language :: Python :: 3.3
Classifier: Programming Language :: Python :: 3.4
Requires-Dist: pyyaml
